{"achievments":[{"name":"discovery","variable":"discovery","values":[5,10,20],"prizes":[100,1000,10000],"stageMultiplier":1.2,"icon":"","title":"Explorer","description":"Discover {x} Entities"},{"name":"reach","variable":"level","values":[5,12,22],"prizes":[100,1000,10000],"stageMultiplier":1.2,"icon":"","title":"Researcher","description":"Reach Level {x}"},{"name":"buy","variable":"buy","values":[50,300,1000],"prizes":[250000,375000,1000000],"stageMultiplier":1.2,"icon":"","title":"Buyer","description":"Buy {x} Entities"},{"name":"merge","variable":"merge","values":[250,750,2000],"prizes":[10000,100000,1000000],"stageMultiplier":1.2,"icon":"","title":"Merger","description":"Merge {x} Times"},{"name":"tap","variable":"tap","values":[30,2000,10000],"prizes":[10000,100000,1000000],"stageMultiplier":1.2,"icon":"","title":"Builder","description":"Tap Generator {x} Times"},{"name":"reveal","variable":"reveal","values":[50,250,1000],"prizes":[50000,350000,50000000],"stageMultiplier":1.2,"icon":"","title":"Adventorous","description":"Open {x} Boxes"},{"name":"mystery","variable":"revealMystery","values":[20,50,150],"prizes":[50000,350000,50000000],"stageMultiplier":1.2,"icon":"","title":"Curious","description":"Open {x} Mystery Crates"}]}